fame/__init__.py
fame/agent.py
fame/parsers.py
fame/config/__init__.py
fame/config/openrouter_models.py
fame/config/replicate_models.py
fame/core/__init__.py
fame/core/abilities_and_knowledge.py
fame/core/environment_and_execution.py
fame/core/facets_of_personality.py
fame/core/mood_and_emotions.py
fame/integrations/__init__.py
fame/integrations/openrouter_integration.py
fame/integrations/replicate_integration.py
fame/integrations/twitter_integration.py
fame/utils/__init__.py
fame/utils/path_utils.py
fame/utils/sentiment_analysis.py
fame/utils/tweet_validator.py
fame_ai-0.0.5.dist-info/METADATA
fame_ai-0.0.5.dist-info/WHEEL
fame_ai-0.0.5.dist-info/top_level.txt
fame_ai-0.0.5.dist-info/RECORD
