Metadata-Version: 2.2
Name: fame-ai
Version: 0.0.5
Summary: FAME Framework (also known as Full AI Meta Engine) is an AI agent framework designed to simulate human-like interactions and content creation on social media platforms, specifically Twitter. It can generate content including images, text, and videos that reflect the agent's personality, knowledge, and current mood. 🎨📝
Author-email: Fame AI <dev@getfame.ai>
License: MIT
Keywords: ai agent,ai framework,x,twitter,integration
Classifier: Development Status :: 3 - Alpha
Classifier: Intended Audience :: Developers
Classifier: License :: OSI Approved :: MIT License
Classifier: Programming Language :: Python :: 3
Classifier: Programming Language :: Python :: 3.8
Classifier: Programming Language :: Python :: 3.9
Classifier: Programming Language :: Python :: 3.10
Classifier: Programming Language :: Python :: 3.11
Requires-Python: >=3.8
Requires-Dist: tweepy>=4.12.0
Requires-Dist: replicate>=0.8.0
Requires-Dist: langchain>=0.1.0
Requires-Dist: langchain-openai>=0.0.2
Requires-Dist: APScheduler>=3.10.0
Requires-Dist: python-dotenv>=1.0.0
Requires-Dist: requests>=2.31.0
Provides-Extra: dev
Requires-Dist: pytest>=7.0.0; extra == "dev"
Requires-Dist: black>=23.0.0; extra == "dev"
Requires-Dist: flake8>=6.0.0; extra == "dev"
Requires-Dist: mypy>=1.0.0; extra == "dev"
